setup.py
coopy/__init__.py
coopy/base.py
coopy/decorators.py
coopy/fileutils.py
coopy/foundation.py
coopy/journal.py
coopy/restore.py
coopy/snapshot.py
coopy/utils.py
coopy.egg-info/PKG-INFO
coopy.egg-info/SOURCES.txt
coopy.egg-info/dependency_links.txt
coopy.egg-info/requires.txt
coopy.egg-info/top_level.txt
coopy/network/__init__.py
coopy/network/default_select.py
coopy/network/linux_epoll.py
coopy/network/network.py
coopy/network/osx_kqueue.py
tests/__init__.py
tests/domain.py
tests/functional/__init__.py
tests/functional/test_coopy.py
tests/unit/__init__.py
tests/unit/test_base.py
tests/unit/test_fileutils.py
tests/unit/test_foundation.py
tests/unit/test_journal.py
tests/unit/test_network.py
tests/unit/test_network_select.py
tests/unit/test_snapshot.py
tests/unit/test_utils.py