Metadata-Version: 1.0
Name: coopy
Version: 0.3.1
Summary: coopy - plain objects persistence/prevalence tool
Home-page: http://coopy.readthedocs.org
Author: Felipe Cruz
Author-email: felipecruz@loogica.net
License: UNKNOWN
Platform: UNKNOWN
